tornado_mail.py
tornado_mail.pyc
tornado_mail-0.4.0.dist-info/DESCRIPTION.rst
tornado_mail-0.4.0.dist-info/METADATA
tornado_mail-0.4.0.dist-info/RECORD
tornado_mail-0.4.0.dist-info/WHEEL
tornado_mail-0.4.0.dist-info/metadata.json
tornado_mail-0.4.0.dist-info/top_level.txt
