Metadata-Version: 2.0
Name: tornado-mail
Version: 0.4.0
Summary: A email plugin for tornado. It is a fake Flask_mail.
Home-page: https://github.com/ruitian/tornado_mail.git
Author: ruitian
Author-email: ike960705@gmail.com
License: UNKNOWN
Platform: UNKNOWN
